CACodeFramework/__init__.py
CACodeFramework/MainWork/CACodeCustomizeAdapter.py
CACodeFramework/MainWork/CACodePureORM.py
CACodeFramework/MainWork/CACodeRepository.py
CACodeFramework/MainWork/__init__.py
CACodeFramework/anno/__init__.py
CACodeFramework/anno/annos.py
CACodeFramework/anno/aop.py
CACodeFramework/cache/__init__.py
CACodeFramework/cacode/Factory.py
CACodeFramework/cacode/Modes.py
CACodeFramework/cacode/Serialize.py
CACodeFramework/cacode/__init__.py
CACodeFramework/exception/__init__.py
CACodeFramework/exception/e_fields.py
CACodeFramework/field/FManage.py
CACodeFramework/field/MySqlDefault.py
CACodeFramework/field/__init__.py
CACodeFramework/opera/CompulsoryRun.py
CACodeFramework/opera/__init__.py
CACodeFramework/opera/op_db.py
CACodeFramework/pojoManager/Manage.py
CACodeFramework/pojoManager/__init__.py
CACodeFramework/pojoManager/tag.py
CACodeFramework/util/Config.py
CACodeFramework/util/DbUtil.py
CACodeFramework/util/Log.py
CACodeFramework/util/ParseUtil.py
CACodeFramework/util/__init__.py
CACodeFramework/util/DBPool/__init__.py
CACodeFramework/util/DBPool/persistent_db.py
CACodeFramework/util/DBPool/persistent_pg.py
CACodeFramework/util/DBPool/pooled_db.py
CACodeFramework/util/DBPool/pooled_pg.py
CACodeFramework/util/DBPool/simple_pooled_db.py
CACodeFramework/util/DBPool/simple_pooled_pg.py
CACodeFramework/util/DBPool/steady_db.py
CACodeFramework/util/DBPool/steady_pg.py
test/__init__.py
test/testFunc.py
test/modules/DatabaseConf.py
test/modules/Demo.py
test/modules/MySqlTest.py
test/modules/SqlServerTest.py
test/modules/__init__.py
util/__init__.py
CACodeFramework-1.3.1.2.dist-info/LICENSE
CACodeFramework-1.3.1.2.dist-info/METADATA
CACodeFramework-1.3.1.2.dist-info/WHEEL
CACodeFramework-1.3.1.2.dist-info/top_level.txt
CACodeFramework-1.3.1.2.dist-info/RECORD
