Metadata-Version: 2.1
Name: CACodeFramework
Version: 1.3.1.2
Summary: CACode Framework For Python Flask,This framework corresponds to the ORM problem,You can see:https://gitee.com/cacode_cctvadmin/CACodeFramework-python-ORM
Home-page: https://gitee.com/cacode_cctvadmin/CACodeFramework-python-ORM
Author: CACode
Author-email: cacode@163.com
License: GPL-3.0
Project-URL: Bug Tracker, https://gitee.com/cacode_cctvadmin/CACodeFramework-python-ORM/issues
Platform: UNKNOWN
Classifier: Programming Language :: Python :: 3
Classifier: License :: OSI Approved :: MIT License
Classifier: Operating System :: OS Independent
Requires-Python: >=3.6
